{"metadata":{"usedHelpers":[],"marked":[],"modules":{"imports":[],"exports":{"exported":[],"specifiers":[]}}},"options":{"filename":"/packages/zurb:foundation-sites/vendor/jquery/src/event/support.js","filenameRelative":"/packages/zurb:foundation-sites/vendor/jquery/src/event/support.js","env":{},"retainLines":false,"highlightCode":true,"suppressDeprecationMessages":false,"presets":[],"plugins":[[[],{"polyfill":false}],[[],null],[[],null],[[],{"allowTopLevelThis":true,"strict":false,"loose":true}],[[],null],[[],null],[[],null],[[],null],[[],null],[[],null],[[],null],[[],null],[[],null],[[],null],[[],null],[[],null],[[],null],[[],{"loose":true}],[[],{"loose":true}],[[],null],[[],{"loose":true}],[[],null],[[],null],[[],null],[[],null],[[],null],[[],null],[[],null],[[],{"loose":true}],[[],null],[[],null],[[],null],[[],null],[[],null],[[],null],[[],null],[[],null]],"ignore":[],"code":true,"metadata":true,"ast":false,"comments":true,"compact":false,"minified":false,"sourceMap":true,"sourceMaps":true,"sourceMapTarget":"/packages/zurb:foundation-sites/vendor/jquery/src/event/support.js.map","sourceFileName":"/packages/zurb:foundation-sites/vendor/jquery/src/event/support.js","babelrc":false,"sourceType":"module","moduleIds":false,"passPerPreset":false,"basename":"support"},"ignored":false,"code":"define([\"../var/support\"], function (support) {\n\n\tsupport.focusin = \"onfocusin\" in window;\n\n\treturn support;\n});","ast":null,"map":{"version":3,"sources":["/packages/zurb:foundation-sites/vendor/jquery/src/event/support.js"],"names":[],"mappings":"AAAA,OAAQ,CACP,gBADO,CAAR,EAEG,UAAU,OAAV,EAAoB;;AAEvB,SAAQ,OAAR,GAAkB,eAAe,MAAjC;;AAEA,QAAO,OAAP;AAEC,CARD","file":"/packages/zurb:foundation-sites/vendor/jquery/src/event/support.js.map","sourcesContent":["define( [\n\t\"../var/support\"\n], function( support ) {\n\nsupport.focusin = \"onfocusin\" in window;\n\nreturn support;\n\n} );\n"]},"hash":"137388cb90e6aee8949c29eeb6df5dc535d2c48c"}
